poochpunt/__init__.py
poochpunt-0.1.dist-info/WHEEL
poochpunt-0.1.dist-info/METADATA
poochpunt-0.1.dist-info/RECORD
